<T3DataStructure>
    <sheets>
        <sDEF>
            <ROOT>
                <sheetTitle>Settings</sheetTitle>
                <type>array</type>
                <el>
                    <settings.emailverify>
                            <label>Action to display</label>
                            <config>
                                <type>select</type>
                                <renderType>selectSingle</renderType>
                                <items type="array">
                                    <numIndex index="0" type="array">
                                        <label>Email Verfication required</label>
                                        <value>emailVerificationRequired</value>
                                    </numIndex>
                                    <numIndex index="1" type="array">
                                        <label>Verify Email</label>
                                        <value>verifyEmail</value>
                                    </numIndex>
                                </items>
                            </config>
                    </settings.emailverify>
                </el>
            </ROOT>
        </sDEF>
    </sheets>
</T3DataStructure>